command_line_blog
