Metadata-Version: 1.0
Name: command-line-blog
Version: 0.1.4
Summary: Publish to the web with just curl!
Home-page: http://github.com/seanbehan/command_line_blog
Author: Sean Behan
Author-email: inbox@seanbehan.com
License: MIT
Platform: UNKNOWN
